{
  "name": "extas/crawlers",
  "package_classes": [
    {
      "class": "extas\\components\\crawlers\\CrawlerRepository",
      "interface": "crawlerRepository"
    }
  ],
  "plugins": [
    {
      "class": "extas\\components\\plugins\\install\\InstallCrawlers",
      "stage": "extas.init.section.crawlers",
      "install_on": "initialization"
    },
    {
      "class": "extas\\components\\plugins\\uninstall\\UninstallCrawlers",
      "stage": "extas.uninstall.section.crawlers",
      "install_on": "initialization"
    }
  ],
  "extensions": [
    {
      "class": "extas\\components\\extensions\\ExtensionRepositoryGet",
      "interface": "extas\\interfaces\\extensions\\IExtensionRepositoryGet",
      "subject": "*",
      "methods": ["crawlerRepository"],
      "install_on": "initialization"
    }
  ]
}